[
  {
    "Id": "1050608",
    "ThreadId": "445457",
    "Html": "Hi,\r<br />\nis there any way to find out if a marker is in a polygon or not?\r<br />\nthanks<br />\n",
    "PostedDate": "2013-05-30T06:20:33.223-07:00",
    "UserRole": null,
    "MarkedAsAnswerDate": null
  },
  {
    "Id": "1050658",
    "ThreadId": "445457",
    "Html": "polygon.IsInside(marker.Position..<br />\n",
    "PostedDate": "2013-05-30T08:00:43.673-07:00",
    "UserRole": null,
    "MarkedAsAnswerDate": null
  },
  {
    "Id": "1051082",
    "ThreadId": "445457",
    "Html": "thanks\r<br />\nIs there any circle area type one to use instead of polygon ?<br />\n",
    "PostedDate": "2013-05-31T01:54:45.287-07:00",
    "UserRole": null,
    "MarkedAsAnswerDate": null
  }
]