[
  {
    "Id": "250144",
    "ThreadId": "73214",
    "Html": "<p>Hi Radioman,</p>\r\n<p>What does this mean and how does it affect usage with regards to licensing?</p>\r\n<p><strong>GoogleMapsAPIKey now is public, sorry ;}</strong></p>\r\n<p>Thanks</p>",
    "PostedDate": "2009-10-27T05:36:55.963-07:00",
    "UserRole": null,
    "MarkedAsAnswerDate": null
  },
  {
    "Id": "250254",
    "ThreadId": "73214",
    "Html": "<p>it change nothing, the google just wanna track what you search, use open street routing if you do not like that ;}</p>",
    "PostedDate": "2009-10-27T10:05:44.483-07:00",
    "UserRole": null,
    "MarkedAsAnswerDate": null
  }
]